adadamp/__init__.py
adadamp/damping.py
adadamp/experiment.py
adadamp-0.1.0.dist-info/LICENSE.txt
adadamp-0.1.0.dist-info/METADATA
adadamp-0.1.0.dist-info/WHEEL
adadamp-0.1.0.dist-info/top_level.txt
adadamp-0.1.0.dist-info/RECORD
