Metadata-Version: 2.1
Name: adadamp
Version: 0.1.0
Summary: Batch size estimation for machine learning training
Home-page: UNKNOWN
Maintainer: Scott Sievert
Maintainer-email: dev@stsievert.com
License: UNKNOWN
Platform: UNKNOWN
Requires-Dist: numpy
Requires-Dist: pandas
